{"type": "Feature", "id": 12514378, "properties": {"woe:id": 12514378, "woe:parent_id": 2264532, "woe:name": "Kentau Airport", "woe:placetype": 14, "woe:placetype_name": "Airport", "woe:lang": "ENG", "iso:country": "KZ", "meta:provider": ["geoplanet:7.3.1", "geoplanet:7.3.2", "geoplanet:7.4.0", "geoplanet:7.4.1", "geoplanet:7.5.1", "geoplanet:7.5.2", "geoplanet:7.6.0", "geoplanet:7.8.1", "geoplanet:7.9.0", "geoplanet:7.10.0", "geoplanet:8.0.0", "woeplanet:8.0.0"], "meta:indexed": "2020-08-20T20:49:06.269590", "meta:updated": "2020-08-22T02:50:17.914960", "woe:hierarchy": {"continent": 24865671, "country": 23424871, "town": 0, "planet": 1, "county": 0, "suburb": 0, "state": 2345982, "region": 0, "localadmin": 0}, "woe:timezone_id": 56043589, "woe:hash": "tx8xqs2hbsqs", "woe:centroid": [68.4888, 43.486099], "geom:latitude": 43.486099, "geom:longitude": 68.4888, "geom:hash": "tx8xqs2hbsqs", "woe:latitude": 43.486099, "geom:centroid": [68.4888, 43.486099], "woe:longitude": 68.4888, "woe:repo": "woeplanet-airport-kz"}, "geometry": {"coordinates": [68.4888, 43.486099], "type": "Point"}}