{"type": "Feature", "id": 12514380, "properties": {"woe:id": 12514380, "woe:parent_id": 2264495, "woe:name": "Khlebodarovskiy Airport", "woe:placetype": 14, "woe:placetype_name": "Airport", "woe:lang": "ENG", "iso:country": "KZ", "meta:provider": ["geoplanet:7.3.1", "geoplanet:7.3.2", "geoplanet:7.4.0", "geoplanet:7.4.1", "geoplanet:7.5.1", "geoplanet:7.5.2", "geoplanet:7.6.0", "geoplanet:7.8.1", "geoplanet:7.9.0", "geoplanet:7.10.0", "geoplanet:8.0.0", "woeplanet:8.0.0"], "meta:indexed": "2020-08-20T20:49:06.271235", "meta:updated": "2020-08-22T02:50:17.915988", "woe:hierarchy": {"continent": 24865671, "country": 23424871, "town": 0, "planet": 1, "county": 0, "suburb": 0, "state": 2345980, "region": 0, "localadmin": 0}, "woe:timezone_id": 56043585, "woe:hash": "v2brmxkz8kem", "woe:centroid": [56.8498, 50.534302], "geom:latitude": 50.534302, "geom:longitude": 56.8498, "geom:hash": "v2brmxkz8kem", "woe:latitude": 50.534302, "geom:centroid": [56.8498, 50.534302], "woe:longitude": 56.8498, "woe:repo": "woeplanet-airport-kz"}, "geometry": {"coordinates": [56.8498, 50.534302], "type": "Point"}}