{"type": "Feature", "id": 12514296, "properties": {"woe:id": 12514296, "woe:parent_id": 2265065, "woe:name": "Bozgyul Airport", "woe:placetype": 14, "woe:placetype_name": "Airport", "woe:lang": "ENG", "iso:country": "KZ", "meta:provider": ["geoplanet:7.3.1", "geoplanet:7.3.2", "geoplanet:7.4.0", "geoplanet:7.4.1", "geoplanet:7.5.1", "geoplanet:7.5.2", "geoplanet:7.6.0", "geoplanet:7.8.1", "geoplanet:7.9.0", "geoplanet:7.10.0", "geoplanet:8.0.0", "woeplanet:8.0.0"], "meta:indexed": "2020-08-20T20:49:06.199404", "meta:updated": "2020-08-22T02:50:17.885469", "woe:hierarchy": {"continent": 24865671, "country": 23424871, "town": 0, "planet": 1, "county": 0, "suburb": 0, "state": 2345990, "region": 0, "localadmin": 0}, "woe:timezone_id": 56043586, "woe:hash": "v25sne7xsnej", "woe:centroid": [61.462502, 45.722301], "geom:latitude": 45.722301, "geom:longitude": 61.462502, "geom:hash": "v25sne7xsnej", "woe:latitude": 45.722301, "geom:centroid": [61.462502, 45.722301], "woe:longitude": 61.462502, "woe:repo": "woeplanet-airport-kz"}, "geometry": {"coordinates": [61.462502, 45.722301], "type": "Point"}}