{"type": "Feature", "id": 12514353, "properties": {"woe:id": 12514353, "woe:parent_id": 2264967, "woe:name": "Kapustin Yar-Turgay Airport", "woe:placetype": 14, "woe:placetype_name": "Airport", "woe:lang": "ENG", "iso:country": "KZ", "meta:provider": ["geoplanet:7.3.1", "geoplanet:7.3.2", "geoplanet:7.4.0", "geoplanet:7.4.1", "geoplanet:7.5.1", "geoplanet:7.5.2", "geoplanet:7.6.0", "geoplanet:7.8.1", "geoplanet:7.9.0", "geoplanet:7.10.0", "geoplanet:8.0.0", "woeplanet:8.0.0"], "meta:indexed": "2020-08-20T20:49:06.248139", "meta:updated": "2020-08-22T02:50:17.906034", "woe:hierarchy": {"continent": 24865671, "country": 23424871, "town": 0, "planet": 1, "county": 0, "suburb": 0, "state": 2345998, "region": 0, "localadmin": 0}, "woe:timezone_id": 56043588, "woe:hash": "v096ujftctjt", "woe:centroid": [46.937099, 48.328499], "geom:latitude": 48.328499, "geom:longitude": 46.937099, "geom:hash": "v096ujftctjt", "woe:latitude": 48.328499, "geom:centroid": [46.937099, 48.328499], "woe:longitude": 46.937099, "woe:repo": "woeplanet-airport-kz"}, "geometry": {"coordinates": [46.937099, 48.328499], "type": "Point"}}