{"type": "Feature", "id": 12514240, "properties": {"woe:id": 12514240, "woe:parent_id": 2345982, "woe:name": "Aays Northeast Airport", "woe:placetype": 14, "woe:placetype_name": "Airport", "woe:lang": "ENG", "iso:country": "KZ", "meta:provider": ["geoplanet:7.3.1", "geoplanet:7.3.2", "geoplanet:7.4.0", "geoplanet:7.4.1", "geoplanet:7.5.1", "geoplanet:7.5.2", "geoplanet:7.6.0", "geoplanet:7.8.1", "geoplanet:7.9.0", "geoplanet:7.10.0", "geoplanet:8.0.0", "woeplanet:8.0.0"], "meta:indexed": "2020-08-20T20:49:06.152139", "meta:updated": "2020-08-22T02:50:17.862716", "woe:hierarchy": {"continent": 24865671, "country": 23424871, "town": 0, "planet": 1, "county": 0, "suburb": 0, "state": 2345982, "region": 0, "localadmin": 0}, "woe:timezone_id": 56043589, "woe:hash": "tx8cx5f134dh", "woe:centroid": [68.865097, 42.472], "geom:latitude": 42.472, "geom:longitude": 68.865097, "geom:hash": "tx8cx5f134dh", "woe:latitude": 42.472, "geom:centroid": [68.865097, 42.472], "woe:longitude": 68.865097, "woe:repo": "woeplanet-airport-kz"}, "geometry": {"coordinates": [68.865097, 42.472], "type": "Point"}}