{"type": "Feature", "id": 12514241, "properties": {"woe:id": 12514241, "woe:parent_id": 2264116, "woe:name": "Abay Bazar Airport", "woe:placetype": 14, "woe:placetype_name": "Airport", "woe:lang": "ENG", "iso:country": "KZ", "meta:provider": ["geoplanet:7.3.1", "geoplanet:7.3.2", "geoplanet:7.4.0", "geoplanet:7.4.1", "geoplanet:7.5.1", "geoplanet:7.5.2", "geoplanet:7.6.0", "geoplanet:7.8.1", "geoplanet:7.9.0", "geoplanet:7.10.0", "geoplanet:8.0.0", "woeplanet:8.0.0"], "meta:indexed": "2020-08-20T20:49:06.152960", "meta:updated": "2020-08-22T02:50:17.863053", "woe:hierarchy": {"continent": 24865671, "country": 23424871, "town": 0, "planet": 1, "county": 0, "suburb": 0, "state": 2345982, "region": 0, "localadmin": 0}, "woe:timezone_id": 56043589, "woe:hash": "tx353cgdte05", "woe:centroid": [68.988197, 41.362598], "geom:latitude": 41.362598, "geom:longitude": 68.988197, "geom:hash": "tx353cgdte05", "woe:latitude": 41.362598, "geom:centroid": [68.988197, 41.362598], "woe:longitude": 68.988197, "woe:repo": "woeplanet-airport-kz"}, "geometry": {"coordinates": [68.988197, 41.362598], "type": "Point"}}