{"type": "Feature", "id": 12514300, "properties": {"woe:id": 12514300, "woe:parent_id": 2264601, "woe:name": "Buzachi Airport", "woe:placetype": 14, "woe:placetype_name": "Airport", "woe:lang": "ENG", "iso:country": "KZ", "meta:provider": ["geoplanet:7.3.1", "geoplanet:7.3.2", "geoplanet:7.4.0", "geoplanet:7.4.1", "geoplanet:7.5.1", "geoplanet:7.5.2", "geoplanet:7.6.0", "geoplanet:7.8.1", "geoplanet:7.9.0", "geoplanet:7.10.0", "geoplanet:8.0.0", "woeplanet:8.0.0"], "meta:indexed": "2020-08-20T20:49:06.202916", "meta:updated": "2020-08-22T02:50:17.886882", "woe:hierarchy": {"continent": 24865671, "country": 23424871, "town": 0, "planet": 1, "county": 0, "suburb": 0, "state": 2345991, "region": 0, "localadmin": 0}, "woe:timezone_id": 56043587, "woe:hash": "v0h90s65vvnx", "woe:centroid": [51.3531, 45.199799], "geom:latitude": 45.199799, "geom:longitude": 51.3531, "geom:hash": "v0h90s65vvnx", "woe:latitude": 45.199799, "geom:centroid": [51.3531, 45.199799], "woe:longitude": 51.3531, "woe:repo": "woeplanet-airport-kz"}, "geometry": {"coordinates": [51.3531, 45.199799], "type": "Point"}}