{"type": "Feature", "id": 12514264, "geometry": {"type": "Point", "coordinates": [62.356499, 51.749802]}, "properties": {"woe:id": 12514264, "woe:parent_id": 2264118, "woe:name": "Altynsarino Airport", "woe:placetype": 14, "woe:placetype_name": "Airport", "woe:lang": "ENG", "iso:country": "KZ", "meta:provider": ["geoplanet:7.3.1", "geoplanet:7.3.2", "geoplanet:7.4.0", "geoplanet:7.4.1", "geoplanet:7.5.1", "geoplanet:7.5.2", "geoplanet:7.6.0", "geoplanet:7.8.1", "geoplanet:7.9.0", "geoplanet:7.10.0", "geoplanet:8.0.0", "woeplanet:8.0.0"], "meta:indexed": "2020-08-20T20:49:06.172392", "meta:updated": "2020-10-14T11:51:06.703892", "woe:hierarchy": {"continent": 24865671, "country": 23424871, "town": 0, "planet": 1, "county": 0, "suburb": 0, "state": 20070176, "region": 0, "localadmin": 0}, "woe:timezone_id": 56043589, "woe:hash": "v3hq6uy87wr9", "woe:centroid": [62.356499, 51.749802], "geom:latitude": 51.749802, "geom:longitude": 62.356499, "geom:hash": "v3hq6uy87wr9", "woe:latitude": 51.749802, "geom:centroid": [62.356499, 51.749802], "woe:longitude": 62.356499, "woe:repo": "woeplanet-airport-kz", "geom:area": 0.0, "woe:scale": 19}}