{"type": "Feature", "id": 12514434, "geometry": {"type": "Point", "coordinates": [69.900398, 42.088902]}, "properties": {"woe:id": 12514434, "woe:parent_id": 2260939, "woe:name": "Pervomayskoye Airport", "woe:placetype": 14, "woe:placetype_name": "Airport", "woe:lang": "ENG", "iso:country": "KZ", "meta:provider": ["geoplanet:7.3.1", "geoplanet:7.3.2", "geoplanet:7.4.0", "geoplanet:7.4.1", "geoplanet:7.5.1", "geoplanet:7.5.2", "geoplanet:7.6.0", "geoplanet:7.8.1", "geoplanet:7.9.0", "geoplanet:7.10.0", "geoplanet:8.0.0", "woeplanet:8.0.0"], "meta:indexed": "2020-08-20T20:49:06.317721", "meta:updated": "2020-10-14T11:51:06.638542", "woe:hierarchy": {"continent": 24865671, "country": 23424871, "town": 0, "planet": 1, "county": 0, "suburb": 0, "state": 2345982, "region": 0, "localadmin": 0}, "woe:timezone_id": 56043589, "woe:hash": "tx3xqw5ctk42", "woe:centroid": [69.900398, 42.088902], "geom:latitude": 42.088902, "geom:longitude": 69.900398, "geom:hash": "tx3xqw5ctk42", "woe:latitude": 42.088902, "geom:centroid": [69.900398, 42.088902], "woe:longitude": 69.900398, "woe:repo": "woeplanet-airport-kz", "geom:area": 0.0, "woe:scale": 19}}