{"type": "Feature", "id": 12514371, "properties": {"woe:id": 12514371, "woe:parent_id": 2258492, "woe:name": "Karoyskiy Airport", "woe:placetype": 14, "woe:placetype_name": "Airport", "woe:lang": "ENG", "iso:country": "KZ", "meta:provider": ["geoplanet:7.3.1", "geoplanet:7.3.2", "geoplanet:7.4.0", "geoplanet:7.4.1", "geoplanet:7.5.1", "geoplanet:7.5.2", "geoplanet:7.6.0", "geoplanet:7.8.1", "geoplanet:7.9.0", "geoplanet:7.10.0", "geoplanet:8.0.0", "woeplanet:8.0.0"], "meta:indexed": "2020-08-20T20:49:06.263371", "meta:updated": "2020-08-22T02:50:17.911931", "woe:hierarchy": {"continent": 24865671, "country": 23424871, "town": 0, "planet": 1, "county": 0, "suburb": 0, "state": 20070180, "region": 0, "localadmin": 0}, "woe:timezone_id": 56043589, "woe:hash": "v8jjj2yhs87y", "woe:centroid": [74.770401, 45.883801], "geom:latitude": 45.883801, "geom:longitude": 74.770401, "geom:hash": "v8jjj2yhs87y", "woe:latitude": 45.883801, "geom:centroid": [74.770401, 45.883801], "woe:longitude": 74.770401, "woe:repo": "woeplanet-airport-kz"}, "geometry": {"coordinates": [74.770401, 45.883801], "type": "Point"}}