{"type": "Feature", "id": 12514367, "properties": {"woe:id": 12514367, "woe:parent_id": 2257827, "woe:name": "Karatomyr Northeast Airport", "woe:placetype": 14, "woe:placetype_name": "Airport", "woe:lang": "ENG", "iso:country": "KZ", "meta:provider": ["geoplanet:7.3.1", "geoplanet:7.3.2", "geoplanet:7.4.0", "geoplanet:7.4.1", "geoplanet:7.5.1", "geoplanet:7.5.2", "geoplanet:7.6.0", "geoplanet:7.8.1", "geoplanet:7.9.0", "geoplanet:7.10.0", "geoplanet:8.0.0", "woeplanet:8.0.0"], "meta:indexed": "2020-08-20T20:49:06.259973", "meta:updated": "2020-08-22T02:50:17.910665", "woe:hierarchy": {"continent": 24865671, "country": 23424871, "town": 0, "planet": 1, "county": 0, "suburb": 0, "state": 2345990, "region": 0, "localadmin": 0}, "woe:timezone_id": 56043586, "woe:hash": "v2j9sb7uzz67", "woe:centroid": [64.198601, 45.2659], "geom:latitude": 45.2659, "geom:longitude": 64.198601, "geom:hash": "v2j9sb7uzz67", "woe:latitude": 45.2659, "geom:centroid": [64.198601, 45.2659], "woe:longitude": 64.198601, "woe:repo": "woeplanet-airport-kz"}, "geometry": {"coordinates": [64.198601, 45.2659], "type": "Point"}}