{"type": "Feature", "id": 12514420, "properties": {"woe:id": 12514420, "woe:parent_id": 2264707, "woe:name": "Nakhimovskiy East Airport", "woe:placetype": 14, "woe:placetype_name": "Airport", "woe:lang": "ENG", "iso:country": "KZ", "meta:provider": ["geoplanet:7.3.1", "geoplanet:7.3.2", "geoplanet:7.4.0", "geoplanet:7.4.1", "geoplanet:7.5.1", "geoplanet:7.5.2", "geoplanet:7.6.0", "geoplanet:7.8.1", "geoplanet:7.9.0", "geoplanet:7.10.0", "geoplanet:8.0.0", "woeplanet:8.0.0"], "meta:indexed": "2020-08-20T20:49:06.305723", "meta:updated": "2020-08-22T02:50:17.930091", "woe:hierarchy": {"continent": 24865671, "country": 23424871, "town": 0, "planet": 1, "county": 0, "suburb": 0, "state": 2345996, "region": 0, "localadmin": 0}, "woe:timezone_id": 56043589, "woe:hash": "v3pdf4rdtd86", "woe:centroid": [66.895302, 51.121201], "geom:latitude": 51.121201, "geom:longitude": 66.895302, "geom:hash": "v3pdf4rdtd86", "woe:latitude": 51.121201, "geom:centroid": [66.895302, 51.121201], "woe:longitude": 66.895302, "woe:repo": "woeplanet-airport-kz"}, "geometry": {"coordinates": [66.895302, 51.121201], "type": "Point"}}