{"type": "Feature", "id": 12514297, "properties": {"woe:id": 12514297, "woe:parent_id": 2256877, "woe:name": "Bugun Aralskoye More Airport", "woe:placetype": 14, "woe:placetype_name": "Airport", "woe:lang": "ENG", "iso:country": "KZ", "meta:provider": ["geoplanet:7.3.1", "geoplanet:7.3.2", "geoplanet:7.4.0", "geoplanet:7.4.1", "geoplanet:7.5.1", "geoplanet:7.5.2", "geoplanet:7.6.0", "geoplanet:7.8.1", "geoplanet:7.9.0", "geoplanet:7.10.0", "geoplanet:8.0.0", "woeplanet:8.0.0"], "meta:indexed": "2020-08-20T20:49:06.200248", "meta:updated": "2020-08-22T02:50:17.885926", "woe:hierarchy": {"continent": 24865671, "country": 23424871, "town": 0, "planet": 1, "county": 0, "suburb": 0, "state": 2345990, "region": 0, "localadmin": 0}, "woe:timezone_id": 56043586, "woe:hash": "v25w2xemdh99", "woe:centroid": [61.198399, 46.1408], "geom:latitude": 46.1408, "geom:longitude": 61.198399, "geom:hash": "v25w2xemdh99", "woe:latitude": 46.1408, "geom:centroid": [61.198399, 46.1408], "woe:longitude": 61.198399, "woe:repo": "woeplanet-airport-kz"}, "geometry": {"coordinates": [61.198399, 46.1408], "type": "Point"}}